botttnet.py
botttnet-0.0.1.dist-info/WHEEL
botttnet-0.0.1.dist-info/METADATA
botttnet-0.0.1.dist-info/RECORD
