Metadata-Version: 2.1
Name: botttnet
Version: 0.0.1
Summary: botttnet
Author: Olli Paloviita
Classifier: License :: OSI Approved :: MIT License
